antiblock_scrapy/__init__.py
antiblock_scrapy/middlewares.py
antiblock_scrapy/tor_controller.py
antiblock_scrapy-0.0.1.dist-info/LICENSE
antiblock_scrapy-0.0.1.dist-info/METADATA
antiblock_scrapy-0.0.1.dist-info/WHEEL
antiblock_scrapy-0.0.1.dist-info/top_level.txt
antiblock_scrapy-0.0.1.dist-info/RECORD
