Metadata-Version: 2.1
Name: antiblock-scrapy
Version: 0.0.1
Summary: Mecanismos antibloqueios para Scrapy
Home-page: https://github.com/elvesrodrigues/antiblock-scrapy
Author: Elves M. Rodrigues
Author-email: elvesmateusrodrigues@gmail.com
License: UNKNOWN
Platform: UNKNOWN
Classifier: Programming Language :: Python :: 3
Classifier: License :: OSI Approved :: MIT License
Classifier: Operating System :: Unix
Requires-Python: >=3.0
Requires-Dist: pysocks (==1.7.1)
Requires-Dist: requests (==2.23.0)
Requires-Dist: stem (==1.8.0)
